pymodaq_plugins_AvaSpec/__init__.py
pymodaq_plugins_AvaSpec/utils.py
pymodaq_plugins_AvaSpec/app/__init__.py
pymodaq_plugins_AvaSpec/app/custom_app_template.py
pymodaq_plugins_AvaSpec/daq_move_plugins/__init__.py
pymodaq_plugins_AvaSpec/daq_viewer_plugins/__init__.py
pymodaq_plugins_AvaSpec/daq_viewer_plugins/plugins_0D/__init__.py
pymodaq_plugins_AvaSpec/daq_viewer_plugins/plugins_1D/__init__.py
pymodaq_plugins_AvaSpec/daq_viewer_plugins/plugins_1D/daq_1Dviewer_AvaSpec.py
pymodaq_plugins_AvaSpec/daq_viewer_plugins/plugins_2D/__init__.py
pymodaq_plugins_AvaSpec/daq_viewer_plugins/plugins_ND/__init__.py
pymodaq_plugins_AvaSpec/exporters/__init__.py
pymodaq_plugins_AvaSpec/extensions/__init__.py
pymodaq_plugins_AvaSpec/hardware/__init__.py
pymodaq_plugins_AvaSpec/models/PIDModelTemplate.py
pymodaq_plugins_AvaSpec/models/__init__.py
pymodaq_plugins_AvaSpec/resources/VERSION
pymodaq_plugins_AvaSpec/resources/__init__.py
pymodaq_plugins_AvaSpec/resources/config_template.toml
pymodaq_plugins_AvaSpec/scanners/__init__.py
pymodaq_plugins_AvaSpec-0.1.2.dist-info/LICENSE
pymodaq_plugins_AvaSpec-0.1.2.dist-info/METADATA
pymodaq_plugins_AvaSpec-0.1.2.dist-info/WHEEL
pymodaq_plugins_AvaSpec-0.1.2.dist-info/entry_points.txt
pymodaq_plugins_AvaSpec-0.1.2.dist-info/top_level.txt
pymodaq_plugins_AvaSpec-0.1.2.dist-info/RECORD
